README.md
setup.py
spotify_graveyard/__init__.py
spotify_graveyard/auth.py
spotify_graveyard/term_input.py
spotify_graveyard.egg-info/PKG-INFO
spotify_graveyard.egg-info/SOURCES.txt
spotify_graveyard.egg-info/dependency_links.txt
spotify_graveyard.egg-info/entry_points.txt
spotify_graveyard.egg-info/requires.txt
spotify_graveyard.egg-info/top_level.txt