Metadata-Version: 1.1
Name: spotify-graveyard
Version: 1.0.1
Summary: Bury the undead tracks in your Inbox playlist once and for all!
Home-page: https://github.com/PhilipTrauner/spotify-graveyard
Author: Philip Trauner
Author-email: philip.trauner@arztpraxis.io
License: MIT
Keywords: spotify ingest
Platform: UNKNOWN
Classifier: Development Status :: 5 - Production/Stable
Classifier: Intended Audience :: Developers
Classifier: License :: OSI Approved :: MIT License
Classifier: Programming Language :: Python :: 3.6
